README.md
setup.py
secretMessageResponse/__init__.py
secretMessageResponse/printMessage.py
secretMessageResponse.egg-info/PKG-INFO
secretMessageResponse.egg-info/SOURCES.txt
secretMessageResponse.egg-info/dependency_links.txt
secretMessageResponse.egg-info/top_level.txt